[
  {
    "Id": "1",
    "MessageBody": "Message 1"
  },
  {
    "Id": "2",
    "MessageBody": "Message 2"
  },
  {
    "Id": "3",
    "MessageBody": "Message 3"
  },
  {
    "Id": "4",
    "MessageBody": "Message 4"
  },
  {
    "Id": "5",
    "MessageBody": "Message 5"
  },
  {
    "Id": "6",
    "MessageBody": "Message 6"
  },
  {
    "Id": "7",
    "MessageBody": "Message 7"
  },
  {
    "Id": "8",
    "MessageBody": "Message 8"
  },
  {
    "Id": "9",
    "MessageBody": "Message 9"
  },
  {
    "Id": "10",
    "MessageBody": "Message 10"
  }
]
